{"case_number":17,"title":"The Secret of the Garden","evidence":["MATCHBOX","CIGARCASE","WATCH","HAIRPIN","INKPOT","BUTTON"],"suspects":["CURATOR","ARTIST","DESIGNER","TAILOR","LIBRARIAN","CARPENTER"],"victim":"CATHERINE","killer":"TAILOR","weapon":"WATCH","crime_scene":"CHAPEL","crime_scene_index":1,"repeated_grids":[0,2],"grids":[{"title":"WINTER GARDEN","grid":[["Z","C","R","T","L","M","B","G","M"],["E","X","L","P","I","I","E","A","X"],["A","K","P","G","B","R","E","M","W"],["C","Z","Q","T","R","M","R","U","A"],["C","A","M","A","A","O","X","M","T"],["T","X","E","I","R","T","B","U","C"],["K","B","D","L","I","Y","J","U","H"],["B","L","E","O","A","Y","T","I","Z"],["U","Y","T","R","N","G","L","H","S"]],"word_cells":{"LIBRARIAN":[[0,4],[1,4],[2,4],[3,4],[4,4],[5,4],[6,4],[7,4],[8,4]],"TAILOR":[[3,3],[4,3],[5,3],[6,3],[7,3],[8,3]],"WATCH":[[2,8],[3,8],[4,8],[5,8],[6,8]]},"victim_word_cells":[],"solution_circle_cells":[[0,1],[1,7],[8,2]],"decoy_circle_cells":[[4,8],[6,4],[5,3]],"circle_cells":[[0,1],[1,7],[8,2],[4,8],[6,4],[5,3]],"evidence":["WATCH"],"suspects":["TAILOR","LIBRARIAN"],"all_words":["WATCH","TAILOR","LIBRARIAN"]},{"title":"CHAPEL","grid":[["E","A","E","B","D","M","D","C","C"],["J","V","C","K","R","A","E","A","I"],["V","C","U","S","I","T","S","T","G"],["W","Q","R","W","G","C","I","H","A"],["M","X","A","C","Z","H","G","E","R"],["Z","V","T","O","T","B","N","R","C"],["K","B","O","X","O","O","E","I","A"],["V","E","R","S","H","X","R","N","S"],["E","Y","X","A","Y","G","A","E","E"]],"word_cells":{"CIGARCASE":[[0,8],[1,8],[2,8],[3,8],[4,8],[5,8],[6,8],[7,8],[8,8]],"MATCHBOX":[[0,5],[1,5],[2,5],[3,5],[4,5],[5,5],[6,5],[7,5]],"DESIGNER":[[0,6],[1,6],[2,6],[3,6],[4,6],[5,6],[6,6],[7,6]],"CURATOR":[[1,2],[2,2],[3,2],[4,2],[5,2],[6,2],[7,2]]},"victim_word_cells":[[0,7],[1,7],[2,7],[3,7],[4,7],[5,7],[6,7],[7,7],[8,7]],"solution_circle_cells":[[7,4],[8,0]],"decoy_circle_cells":[[0,5]],"circle_cells":[[7,4],[8,0],[0,5]],"evidence":["MATCHBOX","CIGARCASE"],"suspects":["CURATOR","DESIGNER"],"all_words":["MATCHBOX","CURATOR","CIGARCASE","DESIGNER"]},{"title":"TROPHY ROOM","grid":[["U","V","B","P","D","E","D","O","W"],["G","B","D","M","Q","K","B","F","N"],["L","I","Z","E","H","I","R","P","B"],["D","N","Y","W","A","T","C","H","U"],["Z","K","F","T","A","I","L","O","R"],["O","P","V","B","B","K","C","V","U"],["M","O","A","R","T","I","S","T","B"],["S","T","H","F","F","B","S","N","W"],["D","P","C","U","E","V","I","C","Z"]],"word_cells":{"TAILOR":[[4,3],[4,4],[4,5],[4,6],[4,7],[4,8]],"INKPOT":[[2,1],[3,1],[4,1],[5,1],[6,1],[7,1]],"ARTIST":[[6,2],[6,3],[6,4],[6,5],[6,6],[6,7]],"WATCH":[[3,3],[3,4],[3,5],[3,6],[3,7]]},"victim_word_cells":[],"solution_circle_cells":[[2,6],[8,6]],"decoy_circle_cells":[[4,4],[6,6]],"circle_cells":[[2,6],[8,6],[4,4],[6,6]],"evidence":["WATCH","INKPOT"],"suspects":["TAILOR","ARTIST"],"all_words":["WATCH","TAILOR","INKPOT","ARTIST"]},{"title":"TRAIN STATION","grid":[["M","B","H","H","S","N","H","S","T"],["G","U","X","S","U","B","Q","Z","N"],["N","T","H","A","I","R","P","I","N"],["Q","T","S","A","R","G","P","A","E"],["E","O","M","E","C","C","E","B","Q"],["W","N","G","P","J","G","Y","L","U"],["C","A","R","P","E","N","T","E","R"],["I","T","G","G","H","E","S","S","U"],["X","W","E","O","T","H","T","J","H"]],"word_cells":{"CARPENTER":[[6,0],[6,1],[6,2],[6,3],[6,4],[6,5],[6,6],[6,7],[6,8]],"HAIRPIN":[[2,2],[2,3],[2,4],[2,5],[2,6],[2,7],[2,8]],"BUTTON":[[0,1],[1,1],[2,1],[3,1],[4,1],[5,1]]},"victim_word_cells":[],"solution_circle_cells":[[2,0],[4,0]],"decoy_circle_cells":[[6,7]],"circle_cells":[[2,0],[4,0],[6,7]],"evidence":["HAIRPIN","BUTTON"],"suspects":["CARPENTER"],"all_words":["HAIRPIN","CARPENTER","BUTTON"]}],"grid_size":9,"difficulty":"medium","date":"2026-08-04","daily_number":17}